airfuse/__init__.py
airfuse/decor.py
airfuse/drivers.py
airfuse/ensemble.py
airfuse/models.py
airfuse/parser.py
airfuse/pm.py
airfuse/style.py
airfuse/util.py
airfuse/mod/__init__.py
airfuse/mod/constant.py
airfuse/mod/geoscf.py
airfuse/mod/goes.py
airfuse/mod/naqfc.py
airfuse/obs/__init__.py
airfuse/obs/epa.py
airfuse/obs/goes.py
airfuse/obs/purpleair.py
airfuse/tests/__init__.py
airfuse/tests/test_drivers.py
airfuse/tests/test_mod.py
airfuse/tests/test_obs.py
airfuse/tests/test_util.py
airfuse-0.8.5.dist-info/LICENSE
airfuse-0.8.5.dist-info/METADATA
airfuse-0.8.5.dist-info/WHEEL
airfuse-0.8.5.dist-info/top_level.txt
airfuse-0.8.5.dist-info/RECORD
