Metadata-Version: 2.1
Name: airfuse
Version: 0.8.5
Summary: airfuse provides several data fusion techniques designed to work with AirNow, PurpleAir, NOAA's Air Quality Forecast and NASA's Composition  Forecast.
Home-page: https://github.com/barronh/airfuse
Author: Barron H. Henderson
Author-email: barronh@gmail.com
Classifier: Programming Language :: Python :: 3
Classifier: License :: OSI Approved :: GNU General Public License v3 (GPLv3)
Classifier: Development Status :: 4 - Beta
Classifier: Operating System :: OS Independent
Requires-Python: >=3.6
License-File: LICENSE
Requires-Dist: xarray >=2023.11.0
Requires-Dist: pandas >=1.1.5
Requires-Dist: numpy <2,>=1.19.5
Requires-Dist: scipy >=1.5.4
Requires-Dist: netCDF4 !=1.7.0,!=1.7.1,>=1.5.8
Requires-Dist: pyproj >=2.6.1
Requires-Dist: pyrsig
Requires-Dist: nna-methods >=0.6.0
Requires-Dist: cfgrib
Requires-Dist: eccodes >=1.2
Requires-Dist: ecmwflibs
